{
  "id": "of_fire_dissonance",
  "weight": 5000,
  "rarity": 2,
  "registry": "affix",
  "lang_file_string": "mmorpg.affix.of_fire_dissonance",
  "type": "suffix",
  "requirements": {
    "list": [
      {
        "min_level": 50,
        "max_level": 2147483647
      },
      {
        "slots": [
          "ring",
          "necklace",
          "bracelet",
          "charm"
        ]
      }
    ]
  },
  "mods": [
    {
      "id": "critical_damage_flat",
      "registry": "stat_mod"
    },
    {
      "id": "low_fire_resist_flat",
      "registry": "stat_mod"
    }
  ]
}