{
  "id": "of_the_hydra",
  "weight": 1250,
  "rarity": 4,
  "registry": "affix",
  "lang_file_string": "mmorpg.affix.of_the_hydra",
  "type": "suffix",
  "requirements": {
    "list": [
      {
        "slots": [
          "helmet",
          "cloth_helmet",
          "leather_helmet"
        ]
      },
      {
        "min_level": 50,
        "max_level": 2147483647
      },
      {
        "min_tier": 10,
        "max_tier": 2147483647
      }
    ]
  },
  "mods": [
    {
      "id": "low_axe_damage_flat",
      "registry": "stat_mod"
    },
    {
      "id": "low_bow_damage_flat",
      "registry": "stat_mod"
    },
    {
      "id": "low_hammer_damage_flat",
      "registry": "stat_mod"
    }
  ]
}